DIGITALNA/Zadace/semafor.vhdl
library ieee;
use ieee.std_logic_1164.all;

entity semafor is
port( clk, rst, t1, t2, t3 : in std_logic;
      output : out std_logic_vector(1 downto 0)
);
end semafor;

architecture beh_semafor of semafor is
    type semafor_states is (R,Y,G,B);
    signal present_state, next_state : semafor_states;

    begin
    -- SEKVENCIJALNI DIO

        process(clk,rst)
        begin
            if (rst = '1') then present_state <= B;
            elsif (rising_edge(clk)) then present_state <= next_state;
            end if;
        end process;

    -- KOMBINACIONI DIO

        process(present_state,t1,t2,t3)
            variable pom : std_logic := '0';
        begin
            case present_state is
                                when B =>   output <= "11";     next_state <= R;    pom := '1';

                                when R =>   if (pom = '1') then 
                                                                output <= "00";
                                                                next_state <= Y; 
                                                                pom := '0';
                                            elsif (t3 = '0') then 
                                                                output <= "00"; 
                                                                next_state <= Y; 
                                            else
                                                                output <= "10";
                                            end if;
                                when Y =>   if (t1 = '0') then 
                                                                output <= "01";
                                                                next_state <= G;
                                            else
                                                                output <= "00";
                                            end if;
                                when G =>   if (t2 = '0') then
                                                                output <= "10"; 
                                                                next_state <= R;
                                            else
                                                                output <= "01";
                                            end if;
            end case;
        end process;

end beh_semafor;

DIGITALNA/Zadace/tb_semafor.vhdl
library ieee;
use ieee.std_logic_1164.all;

entity tb_semafor is
end tb_semafor;

architecture beh_tb_semafor of tb_semafor is

    component semafor is
    port( clk, rst, t1, t2, t3 : in std_logic;
      output : out std_logic_vector(1 downto 0)
    );
    end component;

    signal clk, rst, t1, t2, t3 : std_logic :='0';
    signal output : std_logic_vector(1 downto 0) :="00";

    begin

        hac : semafor port map(
            clk => clk,
            rst => rst,
            t1 => t1,
            t2 => t2,
            t3 => t3,
            output => output
        );

        clock : process
        begin
           
            rst <= '1';  wait for 5 ns;
            assert (output = "11") report "Greska : B" severity error;

            clk <= '1'; wait for 5 ns;
            assert (output = "11") report "Greska : B" severity error;

            clk <= '0';  wait for 5 ns;
            assert (output = "11") report "Greska : B" severity error;

            --------------------------------------------------------------------------------------------

            rst <= '0';  clk <= '1';    wait for 5 ns;
            assert (output = "00") report "Greska : B -> R" severity error;
            clk <= '0';  wait for 5 ns;
            
            clk <= '1';  wait for 5 ns;
            assert (output = "01") report "Greska : R -> Y" severity error;
            clk <= '0';  wait for 5 ns;

            clk <= '1';  wait for 5 ns;
            assert (output = "10") report "Greska : Y -> G" severity error;
            clk <= '0';  wait for 5 ns;

            clk <= '1';  wait for 5 ns;
            assert (output = "00") report "Greska : G -> R" severity error;
            clk <= '0';  wait for 5 ns;

            clk <= '1';  wait for 5 ns;
            assert (output = "01") report "Greska : R -> Y" severity error;
            clk <= '0';  wait for 5 ns;

            clk <= '1';  wait for 5 ns;
            assert (output = "10") report "Greska : Y -> G" severity error;
            clk <= '0';  wait for 5 ns;

            clk <= '1';  wait for 5 ns;
            assert (output = "00") report "Greska : G -> R" severity error;
            clk <= '0';  wait for 5 ns;

            -------------------------------------------------------------------------------------------

            t1 <= '1';  clk <= '1';    wait for 5 ns;
            assert (output = "00") report "Greska : R -> R" severity error;
            clk <= '0';  wait for 5 ns;
            
            clk <= '1';  wait for 5 ns;
            assert (output = "00") report "Greska : R -> R" severity error;
            clk <= '0';  wait for 5 ns;

            t1 <= '0';     
            clk <= '1';  wait for 5 ns;
            assert (output = "01") report "Greska : R -> Y" severity error;
            clk <= '0';  wait for 5 ns;

            t2 <= '1';  clk <= '1';  wait for 5 ns;
            assert (output = "01") report "Greska : Y -> Y" severity error;
            clk <= '0';  wait for 5 ns;            

            t2 <= '0';   
            clk <= '1';  wait for 5 ns;
            assert (output = "10") report "Greska : Y -> G" severity error;
            clk <= '0';  wait for 5 ns;

            t3 <= '1';  clk <= '1';  wait for 5 ns;
            assert (output = "10") report "Greska : G -> G" severity error;
            clk <= '0';  wait for 5 ns;            

            clk <= '1';  wait for 5 ns;
            assert (output = "10") report "Greska : G -> G" severity error;
            clk <= '0';  wait for 5 ns;      

            t3 <= '0';  clk <= '1';  wait for 5 ns;     
            assert (output = "00") report "Greska : G -> R" severity error;
            clk <= '0';  wait for 5 ns; 

            assert false report "Test zavrsen" severity note;
            wait;

        end process;
end beh_tb_semafor;

DIGITALNA/Zadace/semafor_vcd.vcd
$date
  Tue Apr 18 00:32:31 2023
$end
$version
  GHDL v0
$end
$timescale
  1 fs
$end
$scope module standard $end
$upscope $end
$scope module std_logic_1164 $end
$upscope $end
$scope module tb_semafor $end
$var reg 1 ! clk $end
$var reg 1 " rst $end
$var reg 1 # t1 $end
$var reg 1 $ t2 $end
$var reg 1 % t3 $end
$var reg 2 & output[1:0] $end
$scope module hac $end
$var reg 1 ' clk $end
$var reg 1 ( rst $end
$var reg 1 ) t1 $end
$var reg 1 * t2 $end
$var reg 1 + t3 $end
$var reg 2 , output[1:0] $end
$comment present_state is not handled $end
$comment next_state is not handled $end
$upscope $end
$upscope $end
$enddefinitions $end
#0
0!
1"
0#
0$
0%
b11 &
0'
1(
0)
0*
0+
b11 ,
#5000000
1!
1'
#10000000
0!
0'
#15000000
1!
0"
b00 &
1'
0(
b00 ,
#20000000
0!
0'
#25000000
1!
b01 &
1'
b01 ,
#30000000
0!
0'
#35000000
1!
b10 &
1'
b10 ,
#40000000
0!
0'
#45000000
1!
b00 &
1'
b00 ,
#50000000
0!
0'
#55000000
1!
b01 &
1'
b01 ,
#60000000
0!
0'
#65000000
1!
b10 &
1'
b10 ,
#70000000
0!
0'
#75000000
1!
b00 &
1'
b00 ,
#80000000
0!
0'
#85000000
1!
1#
1'
1)
#90000000
0!
0'
#95000000
1!
1'
#100000000
0!
0'
#105000000
1!
0#
b01 &
1'
0)
b01 ,
#110000000
0!
0'
#115000000
1!
1$
1'
1*
#120000000
0!
0'
#125000000
1!
0$
b10 &
1'
0*
b10 ,
#130000000
0!
0'
#135000000
1!
1%
1'
1+
#140000000
0!
0'
#145000000
1!
1'
#150000000
0!
0'
#155000000
1!
0%
b00 &
1'
0+
b00 ,
